.gitignore
CHANGES.rst
MANIFEST.in
README.rst
README.txt
bootstrap.py
buildout.cfg
setup.py
docs/INSTALL.txt
docs/LICENSE.GPL
docs/LICENSE.txt
zest/__init__.py
zest.social.egg-info/PKG-INFO
zest.social.egg-info/SOURCES.txt
zest.social.egg-info/dependency_links.txt
zest.social.egg-info/entry_points.txt
zest.social.egg-info/namespace_packages.txt
zest.social.egg-info/not-zip-safe
zest.social.egg-info/requires.txt
zest.social.egg-info/top_level.txt
zest/social/__init__.py
zest/social/config.py
zest/social/configure.zcml
zest/social/extender.py
zest/social/interfaces.py
zest/social/rebuild_i18n.sh
zest/social/browser/__init__.py
zest/social/browser/addthis.pt
zest/social/browser/configure.zcml
zest/social/browser/viewlets.py
zest/social/browser/zest_social.css
zest/social/locales/manual.pot
zest/social/locales/zest.social.pot
zest/social/locales/nl/LC_MESSAGES/zest.social.mo
zest/social/locales/nl/LC_MESSAGES/zest.social.po
zest/social/profiles/default/browserlayer.xml
zest/social/profiles/default/cssregistry.xml
zest/social/profiles/default/metadata.xml