Metadata-Version: 1.0
Name: zest.social
Version: 1.3
Summary: Zest Social Bookmarking
Home-page: https://github.com/zestsoftware/zest.social
Author: Zest Software
Author-email: info@zestsoftware.nl
License: GPL
Keywords: social bookmarking addthis
Platform: UNKNOWN
Classifier: Framework :: Plone
Classifier: Framework :: Plone :: 3.3
Classifier: Framework :: Plone :: 4.0
Classifier: Framework :: Plone :: 4.1
Classifier: Framework :: Plone :: 4.2
Classifier: Programming Language :: Python
